{
    "version": "1.17.0",
    "description": "Cross Platform Rust Repl",
    "homepage": "https://github.com/sigmaSd/IRust",
    "license": "MIT",
    "architecture": {
        "64bit": {
            "url": "https://github.com/sigmaSd/IRust/releases/download/1.17.0/irust-1.17.0-x86_64-pc-windows-msvc.zip",
            "hash": "bc901cac6ecb59a1de605b49fc081c3bd7ddbebbddd1e57a757a4ee5ab5378fc",
            "extract_dir": "irust-1.17.0-x86_64-pc-windows-msvc"
        }
    },
    "bin": "irust.exe",
    "checkver": "github",
    "autoupdate": {
        "architecture": {
            "64bit": {
                "url": "https://github.com/sigmaSd/IRust/releases/download/$version/irust-$version-x86_64-pc-windows-msvc.zip",
                "extract_dir": "irust-$version-x86_64-pc-windows-msvc"
            }
        }
    }
}
