{
    "homepage": "https://github.com/rxi/lite",
    "version": "1.06",
    "description": "A lightweight text editor written in Lua.",
    "license": "MIT",
    "url": "https://github.com/rxi/lite/releases/download/v1.06/lite.zip",
    "hash": "08d06555768fc861df202cf6e252e33a4af5b02c38d9a8a6898b69c05637bfce",
    "bin": "lite.exe",
    "shortcuts": [
        [
            "lite.exe",
            "lite"
        ]
    ],
    "persist": "data/user",
    "checkver": "github",
    "autoupdate": {
        "url": "https://github.com/rxi/lite/releases/download/v$version/lite.zip"
    }
}
